README.md
config.example.toml
logger.example.toml
tgl2rdm/__init__.py
tgl2rdm/__main__.py
tgl2rdm/cli/__init__.py
tgl2rdm/cli/config.py
tgl2rdm/cli/main.py
tgl2rdm/cli/tgl.py
tgl2rdm/cli/utils.py
tgl2rdm/config.py
tgl2rdm/extract.py
tgl2rdm/http.py
tgl2rdm/load.py
tgl2rdm/transform.py
tgl2rdm/utils.py
tgl2rdm-0.1.4.dist-info/entry_points.txt
tgl2rdm-0.1.4.dist-info/WHEEL
tgl2rdm-0.1.4.dist-info/METADATA
tgl2rdm-0.1.4.dist-info/RECORD
